telentfy/__init__.py
telentfy-0.0.3.dist-info/LICENSE
telentfy-0.0.3.dist-info/METADATA
telentfy-0.0.3.dist-info/WHEEL
telentfy-0.0.3.dist-info/RECORD
